xlsx_streaming/__init__.py
xlsx_streaming/render.py
xlsx_streaming/streaming.py
xlsx_streaming/xlsx_template.py
xlsx_streaming-2.0.1.dist-info/licenses/LICENSE
xlsx_streaming-2.0.1.dist-info/METADATA
xlsx_streaming-2.0.1.dist-info/WHEEL
xlsx_streaming-2.0.1.dist-info/top_level.txt
xlsx_streaming-2.0.1.dist-info/RECORD
