Metadata-Version: 2.4
Name: xlsx_streaming
Version: 2.0.1
Summary: Export your data as an xlsx stream
Home-page: https://github.com/Polyconseil/xlsx_streaming/
Author: Polyconseil
Author-email: opensource+xlsx_streaming@polyconseil.fr
Maintainer: Polyconseil
Maintainer-email: opensource+xlsx_streaming@polyconseil.fr
License: GNU GPLv3
Keywords: xlsx,excel,streaming
Platform: any
Classifier: Development Status :: 5 - Production/Stable
Classifier: Intended Audience :: Developers
Classifier: License :: OSI Approved :: GNU General Public License v3 (GPLv3)
Classifier: Natural Language :: English
Classifier: Operating System :: OS Independent
Classifier: Programming Language :: Python :: 3.8
Classifier: Programming Language :: Python :: 3.9
Classifier: Programming Language :: Python :: 3.10
Classifier: Programming Language :: Python :: 3.11
Classifier: Programming Language :: Python :: 3.12
Requires-Python: >=3.8
License-File: LICENSE
Requires-Dist: zipstream>=1.1.3
Dynamic: license-file
